pydorks/__init__.py
pydorks-0.6.dist-info/LICENSE
pydorks-0.6.dist-info/METADATA
pydorks-0.6.dist-info/WHEEL
pydorks-0.6.dist-info/top_level.txt
pydorks-0.6.dist-info/RECORD
