Metadata-Version: 2.1
Name: pydorks
Version: 0.6
Summary: Recherchez du contenu sur Google efficacement.
Home-page: UNKNOWN
Author: billythegoat356
Author-email: <billythegoat356356@gmail.com>
License: Eclipse Public License 2.0
Keywords: python,google,google dorks,dorks,gdorks
Platform: UNKNOWN
